oxidize_postal-0.1.2.dist-info/METADATA
oxidize_postal-0.1.2.dist-info/WHEEL
oxidize_postal/__init__.py
oxidize_postal/oxidize_postal.cpython-312-darwin.so
oxidize_postal-0.1.2.dist-info/RECORD
