Metadata-Version: 2.4
Name: oxidize-postal
Version: 0.1.2
Classifier: Development Status :: 4 - Beta
Classifier: Intended Audience :: Developers
Classifier: License :: OSI Approved :: MIT License
Classifier: Programming Language :: Python :: 3
Classifier: Programming Language :: Python :: 3.9
Classifier: Programming Language :: Python :: 3.10
Classifier: Programming Language :: Python :: 3.11
Classifier: Programming Language :: Python :: 3.12
Classifier: Programming Language :: Rust
Classifier: Topic :: Software Development :: Libraries :: Python Modules
Classifier: Topic :: Text Processing
Classifier: Topic :: Scientific/Engineering :: GIS
Summary: High-performance postal address parser and normalizer using libpostal with Rust bindings
Keywords: address,postal,parsing,normalization,libpostal,rust,performance
Author-email: Eric Aleman <eric@example.com>
Requires-Python: >=3.9
Project-URL: Repository, https://github.com/ericaleman/oxidize-postal
